insightaid/__init__.py
insightaid-0.0.1.dist-info/licenses/LICENSE
insightaid-0.0.1.dist-info/METADATA
insightaid-0.0.1.dist-info/WHEEL
insightaid-0.0.1.dist-info/top_level.txt
insightaid-0.0.1.dist-info/RECORD
