Metadata-Version: 2.4
Name: insightaid
Version: 0.0.1
Summary: Private, on-device AI accessibility assistant powered by Gemma
Home-page: https://github.com/ontaptom/insightaid
Author: Tomek Porozynski
Author-email: tomasz.porozynski@gmail.com
Classifier: Development Status :: 1 - Planning
Classifier: Intended Audience :: End Users/Desktop
Classifier: Topic :: Scientific/Engineering :: Artificial Intelligence
Classifier: License :: OSI Approved :: Apache Software License
Classifier: Programming Language :: Python :: 3
Classifier: Operating System :: Microsoft :: Windows
Requires-Python: >=3.8
License-File: LICENSE
Dynamic: author
Dynamic: author-email
Dynamic: classifier
Dynamic: description
Dynamic: description-content-type
Dynamic: home-page
Dynamic: license-file
Dynamic: requires-python
Dynamic: summary
